cmarkgfm/__init__.py
cmarkgfm/_cmark.abi3.so
cmarkgfm/build_cmark.py
cmarkgfm/cmark.cffi.h
cmarkgfm/cmark.py
cmarkgfm/cmark_module.h
cmarkgfm-2025.10.22.dist-info/METADATA
cmarkgfm-2025.10.22.dist-info/WHEEL
cmarkgfm-2025.10.22.dist-info/top_level.txt
cmarkgfm-2025.10.22.dist-info/RECORD
cmarkgfm-2025.10.22.dist-info/licenses/LICENSE.txt
