Metadata-Version: 2.4
Name: cmarkgfm
Version: 2025.10.22
Summary: Minimal bindings to GitHub's fork of cmark
Author-email: The Python Packaging Authority <me@thea.codes>, pypa-dev@googlegroups.com
License-Expression: MIT
Project-URL: Homepage, https://github.com/theacodes/cmarkgfm
Project-URL: Bug Reports, https://github.com/theacodes/cmarkgfm/issues
Project-URL: Funding, https://donate.pypi.org
Project-URL: Source, https://github.com/theacodes/cmarkgfm
Classifier: Development Status :: 5 - Production/Stable
Classifier: Intended Audience :: Developers
Classifier: Topic :: Software Development :: Build Tools
Classifier: Programming Language :: Python :: 3
Classifier: Programming Language :: Python :: 3.9
Classifier: Programming Language :: Python :: 3.10
Classifier: Programming Language :: Python :: 3.11
Classifier: Programming Language :: Python :: 3.12
Classifier: Programming Language :: Python :: 3.13
Classifier: Programming Language :: Python :: 3.14
Requires-Python: >=3.9
License-File: LICENSE.txt
Requires-Dist: cffi>=2.0.0
Dynamic: license-file
